AUTHORS.txt
LICENSE.txt
README.md
setup.py
cadCAD/__init__.py
cadCAD/configuration/__init__.py
cadCAD/configuration/utils/__init__.py
cadCAD/configuration/utils/depreciationHandler.py
cadCAD/configuration/utils/policyAggregation.py
cadCAD/configuration/utils/userDefinedObject.py
cadCAD/engine/__init__.py
cadCAD/engine/execution.py
cadCAD/engine/simulation.py
cadCAD/engine/utils.py
cadCAD/utils/__init__.py
cadCAD/utils/execution.py
cadCAD/utils/jupyter.py
cadCAD/utils/sys_config.py
cadCAD_legacy_devel.egg-info/PKG-INFO
cadCAD_legacy_devel.egg-info/SOURCES.txt
cadCAD_legacy_devel.egg-info/dependency_links.txt
cadCAD_legacy_devel.egg-info/requires.txt
cadCAD_legacy_devel.egg-info/top_level.txt
documentation/__init__.py
documentation/examples/__init__.py
documentation/examples/example_1.py
documentation/examples/historical_state_access.py
documentation/examples/param_sweep.py
documentation/examples/policy_aggregation.py
documentation/examples/sys_model_A.py
documentation/examples/sys_model_AB_exec.py
documentation/examples/sys_model_A_exec.py
documentation/examples/sys_model_B.py
documentation/examples/sys_model_B_exec.py
simulations/__init__.py
simulations/regression_tests/__init__.py
simulations/regression_tests/experiments.py
simulations/regression_tests/execs/__init__.py
simulations/regression_tests/execs/config1_test.py
simulations/regression_tests/execs/config2_test.py
simulations/regression_tests/execs/multi_config_test.py
simulations/regression_tests/execs/multi_config_test2.py
simulations/regression_tests/execs/param_sweep_test.py
simulations/regression_tests/execs/policy_agg_test.py
simulations/regression_tests/models/__init__.py
simulations/regression_tests/models/config1.py
simulations/regression_tests/models/config2.py
simulations/regression_tests/models/config_multi_1.py
simulations/regression_tests/models/config_multi_2.py
simulations/regression_tests/models/param_sweep.py
simulations/regression_tests/models/policy_aggregation.py
simulations/regression_tests/models/sweep_config.py
testing/__init__.py
testing/generic_test.py
testing/results_comparison.py
testing/utils.py
testing/experiments/__init__.py
testing/models/__init__.py
testing/models/param_sweep.py
